lab2/sum/fulladder.v
module full_adder(S, Cout, A, B, Cin);
   output S;
   output Cout;
   input  A;
   input  B;
   input  Cin;
   
   wire   w1;
   wire   w2;
   wire   w3;
   wire   w4;
   
   xor(w1, A, B);
   xor(S, Cin, w1);
   and(w2, A, B);   
   and(w3, A, Cin);
   and(w4, B, Cin);   
   or(Cout, w2, w3, w4);
endmodule

lab2/sum/sum.v
module sumadorestador(S, C, V, A, B, Op);
   output [3:0] S;   // The 4-bit sum/difference.
   output 	C;   // The 1-bit carry/borrow status.
   output 	V;   // The 1-bit overflow status.
   input [3:0] 	A;   
   input [3:0] 	B;   
   input 	Op;  // The operation: 0 => Add, 1=>Subtract.
   
   wire 	C0; // The carry out bit of fa0, the carry in bit of fa1.
   wire 	C1; // The carry out bit of fa1, the carry in bit of fa2.
   wire 	C2; // The carry out bit of fa2, the carry in bit of fa3.
   wire 	C3; // The carry out bit of fa2, used to generate final carry/borrrow.
   
   wire 	B0; // The xor'd result of B[0] and Op
   wire 	B1; // The xor'd result of B[1] and Op
   wire 	B2; // The xor'd result of B[2] and Op
   wire 	B3; // The xor'd result of B[3] and Op

    
   xor(B0, B[0], Op);
   xor(B1, B[1], Op);
   xor(B2, B[2], Op);
   xor(B3, B[3], Op);
   xor(C, C3, Op);     // Carry = C3 for addition, Carry = not(C3) for subtraction.
   xor(V, C3, C2);     // If the two most significant carry output bits differ, then we have an overflow.
   
   full_adder fa0(S[0], C0, A[0], B0, Op);    // Least significant bit.
   full_adder fa1(S[1], C1, A[1], B1, C0);
   full_adder fa2(S[2], C2, A[2], B2, C1);
   full_adder fa3(S[3], C3, A[3], B3, C2);    // Most significant bit.
endmodule

lab2/sum/sum_tb.v
module testbench_sumadorestador();
   // Inputs
   reg [3:0] A;
   reg [3:0] B;
   reg Op;
   
   // Outputs
   wire [3:0] S;
   wire C;
   wire V;
   
   // Instantiate the sumadorestador module
   sumadorestador uut(
      .S(S),
      .C(C),
      .V(V),
      .A(A),
      .B(B),
      .Op(Op)
   );
   
   // Monitor outputs
   initial begin
      $monitor("A = %b, B = %b, Op = %b, S = %b, C = %b, V = %b", A, B, Op, S, C, V);
      
      // Test Case 1: Addition (Op=0)
      A = 4'b0110;
      B = 4'b1010;
      Op = 1'b0;
      #10; // Wait for 10 time units
      
      // Test Case 2: Subtraction (Op=1)
      A = 4'b0110;
      B = 4'b1010;
      Op = 1'b1;
      #10; // Wait for 10 time units

      // Test Case 3: Overflow in Addition
      A = 4'b1111;
      B = 4'b0001;
      Op = 1'b0;
      #10; // Wait for 10 time units
      
      // Test Case 4: Zero Result in Addition
A = 4'b0101;
B = 4'b1011;
Op = 1'b0;
#10; // Wait for 10 time units
// Expected output: S=4'b0000, C=1'b0, V=1'b0

// Test Case 5: Zero Result in Subtraction
A = 4'b0101;
B = 4'b0101;
Op = 1'b1;
#10; // Wait for 10 time units
// Expected output: S=4'b0000, C=1'b1, V=1'b0

// Test Case 6: Large Addition (No Overflow)
A = 4'b1101;
B = 4'b0011;
Op = 1'b0;
#10; // Wait for 10 time units
// Expected output: S=4'b10000, C=1'b0, V=1'b0

// Test Case 7: Large Subtraction (No Overflow)
A = 4'b1101;
B = 4'b0011;
Op = 1'b1;
#10; // Wait for 10 time units
// Expected output: S=4'b01100, C=1'b1, V=1'b1

// Test Case 8: Large Addition (Overflow)
A = 4'b1111;
B = 4'b0111;
Op = 1'b0;
#10; // Wait for 10 time units
// Expected output: S=4'b11111, C=1'b1, V=1'b1

// Test Case 9: Large Subtraction (Overflow)
A = 4'b1001;
B = 4'b1101;
Op = 1'b1;
#10; // Wait for 10 time units
// Expected output: S=4'b11100, C=1'b0, V=1'b1
      
      // End the simulation
      $finish;
   end

    // WAVES IN VCD TO OPEN IN GTKWAVE
  initial
  begin
    $dumpfile("top.vcd");
    $dumpvars(0, testbench_sumadorestador);
  end
endmodule

lab2/sum/top.vcd
$date
	Mon Oct  2 23:00:10 2023
$end
$version
	Icarus Verilog
$end
$timescale
	1s
$end
$scope module testbench_sumadorestador $end
$var wire 1 ! V $end
$var wire 4 " S [3:0] $end
$var wire 1 # C $end
$var reg 4 $ A [3:0] $end
$var reg 4 % B [3:0] $end
$var reg 1 & Op $end
$scope module uut $end
$var wire 4 ' A [3:0] $end
$var wire 4 ( B [3:0] $end
$var wire 1 ) B0 $end
$var wire 1 * B1 $end
$var wire 1 + B2 $end
$var wire 1 , B3 $end
$var wire 1 # C $end
$var wire 1 & Op $end
$var wire 1 ! V $end
$var wire 4 - S [3:0] $end
$var wire 1 . C3 $end
$var wire 1 / C2 $end
$var wire 1 0 C1 $end
$var wire 1 1 C0 $end
$scope module fa0 $end
$var wire 1 2 A $end
$var wire 1 ) B $end
$var wire 1 & Cin $end
$var wire 1 1 Cout $end
$var wire 1 3 S $end
$var wire 1 4 w1 $end
$var wire 1 5 w2 $end
$var wire 1 6 w3 $end
$var wire 1 7 w4 $end
$upscope $end
$scope module fa1 $end
$var wire 1 8 A $end
$var wire 1 * B $end
$var wire 1 1 Cin $end
$var wire 1 0 Cout $end
$var wire 1 9 S $end
$var wire 1 : w1 $end
$var wire 1 ; w2 $end
$var wire 1 < w3 $end
$var wire 1 = w4 $end
$upscope $end
$scope module fa2 $end
$var wire 1 > A $end
$var wire 1 + B $end
$var wire 1 0 Cin $end
$var wire 1 / Cout $end
$var wire 1 ? S $end
$var wire 1 @ w1 $end
$var wire 1 A w2 $end
$var wire 1 B w3 $end
$var wire 1 C w4 $end
$upscope $end
$scope module fa3 $end
$var wire 1 D A $end
$var wire 1 , B $end
$var wire 1 / Cin $end
$var wire 1 . Cout $end
$var wire 1 E S $end
$var wire 1 F w1 $end
$var wire 1 G w2 $end
$var wire 1 H w3 $end
$var wire 1 I w4 $end
$upscope $end
$upscope $end
$upscope $end
$enddefinitions $end
$comment Show the parameter values. $end
$dumpall
$end
#0
$dumpvars
1I
0H
0G
1F
0E
0D
0C
1B
0A
1@
0?
1>
0=
0<
1;
0:
09
18
07
06
05
04
03
02
01
10
1/
1.
b0 -
1,
0+
1*
0)
b1010 (
b110 '
0&
b1010 %
b110 $
1#
b0 "
0!
$end
#10
1<
1B
1!
11
09
10
1?
1E
0.
14
17
1:
0;
0@
1A
1C
0F
0I
1)
0*
1+
0,
1#
b1100 "
b1100 -
03
1&
#20
0!
0?
0E
1.
1@
0A
0C
04
15
1F
1H
0+
1#
b0 "
b0 -
03
07
12
1D
0&
b1 %
b1 (
b1111 $
b1111 '
#30
1/
0?
1B
0!
1#
1=
1I
09
10
b0 "
b0 -
0E
1.
1*
1,
1:
0<
1F
0H
08
0D
b1011 %
b1011 (
b101 $
b101 '
#40
14
05
0)
0#
b0 "
b0 -
03
16
07
1&
b101 %
b101 (
#50
1.
0E
0!
1/
0?
1B
10
09
1=
04
15
0I
11
1H
1)
0,
1#
b0 "
b0 -
03
06
1D
0&
b11 %
b11 (
b1101 $
b1101 '
#60
0B
19
00
0?
1E
14
05
0:
0=
0@
1A
0C
0F
1G
1I
0)
0*
1+
1,
0#
b1010 "
b1010 -
03
16
07
1&
#70
1=
1?
1B
1C
0E
19
10
04
15
1F
0G
0I
11
1;
1<
1)
1*
0,
1#
b110 "
b110 -
03
06
18
0&
b111 %
b111 (
b1111 $
b1111 '
#80
0.
1E
0H
0!
09
0/
14
05
0C
1:
0;
0<
0A
0B
0)
0+
1#
b1100 "
b1100 -
03
16
07
08
0>
1&
b1101 %
b1101 (
b1001 $
b1001 '
